<?xml version="1.0" encoding="utf-8"?>
<resources>

    <color name="judo_red">#FFEB372D</color>
    <color name="judo_white">#FFFAFAFA</color>
    <color name="judo_teal">#FF48B6AC</color>
    <color name="judo_dark_teal">#FF40A098</color>
    <color name="judo_blue">#FF1E78A0</color>
    <color name="judo_dark_blue">#186080</color>
    <color name="judo_white_90">#E6FFFFFF</color>

    <color name="judo_black_16">#28000000</color>
    <color name="judo_black_38">#60000000</color>
    <color name="judo_black_54">#89000000</color>
    <color name="judo_black_87">#DE000000</color>

</resources>